setup.py
external_user_provision_tool.egg-info/PKG-INFO
external_user_provision_tool.egg-info/SOURCES.txt
external_user_provision_tool.egg-info/dependency_links.txt
external_user_provision_tool.egg-info/entry_points.txt
external_user_provision_tool.egg-info/not-zip-safe
external_user_provision_tool.egg-info/requires.txt
external_user_provision_tool.egg-info/top_level.txt
project/__init__.py
project/mail.py
project/plugin.py
project/user_provision.py
project/plugins/__init__.py
project/plugins/artifactory/__init__.py
project/plugins/aws/__init__.py
project/plugins/azure/__init__.py
project/plugins/bitbucket/__init__.py
project/plugins/jira/__init__.py
project/plugins/papertrail/__init__.py
project/plugins/slack/__init__.py