Metadata-Version: 1.0
Name: external-user-provision-tool
Version: 1.22
Summary: Add and remove users from multiple web services with desired permissions
Home-page: https://github.com/Signiant/External-user-provisioning
Author: Eric Laroche
Author-email: elaroche@signiant.com
License: MIT
Platform: UNKNOWN
